AUTHORS
CHANGELOG.txt
DESCRIPTION
LICENSE
MANIFEST.in
README.md
setup.py
djangocms_markdown/__init__.py
djangocms_markdown/cms_plugins.py
djangocms_markdown/models.py
djangocms_markdown.egg-info/PKG-INFO
djangocms_markdown.egg-info/SOURCES.txt
djangocms_markdown.egg-info/dependency_links.txt
djangocms_markdown.egg-info/pbr.json
djangocms_markdown.egg-info/requires.txt
djangocms_markdown.egg-info/top_level.txt
djangocms_markdown/migrations/0001_initial.py
djangocms_markdown/migrations/__init__.py
djangocms_markdown/south_migrations/0001_initial.py
djangocms_markdown/south_migrations/__init__.py
djangocms_markdown/static/djangocms_markdown/js/epiceditor.js
djangocms_markdown/static/djangocms_markdown/js/epiceditor.min.js
djangocms_markdown/static/djangocms_markdown/js/jquery-3.1.0.min.js
djangocms_markdown/static/djangocms_markdown/themes/base/epiceditor.css
djangocms_markdown/static/djangocms_markdown/themes/editor/epic-dark.css
djangocms_markdown/static/djangocms_markdown/themes/editor/epic-light.css
djangocms_markdown/static/djangocms_markdown/themes/preview/bartik.css
djangocms_markdown/static/djangocms_markdown/themes/preview/github.css
djangocms_markdown/static/djangocms_markdown/themes/preview/preview-dark.css
djangocms_markdown/templates/djangocms_markdown/change_form.html
djangocms_markdown/templates/djangocms_markdown/markdown.html