Metadata-Version: 1.0
Name: djangocms-markdown
Version: 0.3.2
Summary: A plugin for django-cms that aims to replace the standard text plugin with it's
